glik_sdk/__init__.py
glik_sdk/client.py
glik_sdk-0.0.1.dist-info/METADATA
glik_sdk-0.0.1.dist-info/WHEEL
glik_sdk-0.0.1.dist-info/top_level.txt
glik_sdk-0.0.1.dist-info/RECORD
