Metadata-Version: 2.1
Name: glik-sdk
Version: 0.0.1
Summary: A Python SDK for integrating to the Glik Service-API
Home-page: https://github.com/rivalz-glik/glik-sdk
Author: Glik
Author-email: engineer@glik.ai
License: MIT
Project-URL: Bug Tracker, https://github.com/rivalz-glik/glik-sdk/issues
Project-URL: Documentation, https://github.com/rivalz-glik/glik-sdk#readme
Keywords: glik ai language-processing api sdk
Platform: UNKNOWN
Classifier: Development Status :: 3 - Alpha
Classifier: Intended Audience :: Developers
Classifier: Operating System :: OS Independent
Classifier: Programming Language :: Python :: 3
Classifier: Programming Language :: Python :: 3.6
Classifier: Programming Language :: Python :: 3.7
Classifier: Programming Language :: Python :: 3.8
Classifier: Programming Language :: Python :: 3.9
Classifier: Programming Language :: Python :: 3.10
Classifier: Programming Language :: Python :: 3.11
Classifier: Topic :: Software Development :: Libraries :: Python Modules
Requires-Python: >=3.6
Requires-Dist: requests>=2.25.1
Requires-Dist: pydantic>=1.8.2
Provides-Extra: dev
Requires-Dist: pytest>=6.0; extra == "dev"
Requires-Dist: pytest-cov>=2.0; extra == "dev"
Requires-Dist: black>=21.0; extra == "dev"
Requires-Dist: isort>=5.0; extra == "dev"
Requires-Dist: flake8>=3.9; extra == "dev"
Requires-Dist: mypy>=0.910; extra == "dev"
